{
  "Schedules": [
    {
      "MediaList": [
        {
          "MediaType": {
            "Type": "website"
          },
          "MediaUri": {
            "Uri": "google.com"
          },
          "MediaDuration": {
            "DurationInSeconds": "20"
          },
        },
        {
          "MediaType": {
            "Type": "website"
          },
          "MediaUri": {
            "Uri": "github.com"
          },
          "MediaDuration": {
            "DurationInSeconds": "20"
          },
        }
      ],
      "ScheduleTimeConfig": []
    }
  ],
  "TargetScreenInfo": {
    "ScreenName": "test",
    "RemoteConfigFileName": "testFile.json"
  }
}
